esql_parser/EsqlBaseLexer.py
esql_parser/EsqlBaseParser.py
esql_parser/EsqlBaseParserListener.py
esql_parser-9.1.3.dist-info/licenses/LICENSE
esql_parser-9.1.3.dist-info/licenses/NOTICE.txt
esql_parser-9.1.3.dist-info/METADATA
esql_parser-9.1.3.dist-info/WHEEL
esql_parser-9.1.3.dist-info/top_level.txt
esql_parser-9.1.3.dist-info/RECORD
