Metadata-Version: 2.4
Name: esql-parser
Version: 9.1.3
Summary: Python parser for Elasticsearch ESQL
Author-email: Michael Bischoff <michael@bischoff.dev>
License-Expression: Elastic-2.0
Project-URL: Homepage, https://github.com/mjmbischoff/esql-check
Project-URL: Issues, https://github.com/mjmbischoff/esql-check/issues
Classifier: Programming Language :: Python :: 3
Classifier: Operating System :: OS Independent
Requires-Python: >=3.8
License-File: LICENSE
License-File: NOTICE.txt
Requires-Dist: antlr4-python3-runtime==4.13.1
Dynamic: license-file
